sandlermisc/__init__.py
sandlermisc/gas_constant.py
sandlermisc/statereporter.py
sandlermisc/thermals.py
sandlermisc-0.3.2.dist-info/METADATA
sandlermisc-0.3.2.dist-info/WHEEL
sandlermisc-0.3.2.dist-info/licenses/LICENSE
sandlermisc-0.3.2.dist-info/RECORD
